Metadata-Version: 2.1
Name: odoo14-addon-brand
Version: 14.0.1.0.3
Summary: This is a base addon for brand modules. It adds the brand object and its menu and define an abstract model to be inherited from branded objects
Home-page: https://github.com/OCA/brand
Author: Odoo Community Association (OCA),ACSONE SA/NV
Author-email: support@odoo-community.org
License: AGPL-3
Platform: UNKNOWN
Classifier: Programming Language :: Python
Classifier: Framework :: Odoo
Classifier: Framework :: Odoo :: 14.0
Classifier: License :: OSI Approved :: GNU Affero General Public License v3
Requires-Python: >=3.6
Requires-Dist: odoo <14.1dev,>=14.0a
